absd/__init__.py
absd/messages.py
absd-0.1.4.dist-info/licenses/LICENSE
absd-0.1.4.dist-info/METADATA
absd-0.1.4.dist-info/WHEEL
absd-0.1.4.dist-info/top_level.txt
absd-0.1.4.dist-info/RECORD
